Workbook

Sheet Raw Data
A1: Financial Year | B1: Revenue (₹ Cr) | C1: Revenue Growth (%) | D1: Net Profit (₹ Cr) | E1: Net Profit Margin (%) | F1: Total Assets (₹ Cr) | G1: Total Equity (₹ Cr) | H1: Current Assets (₹ Cr) | I1: Current Liabilities (₹ Cr) | J1: Current Ratio (x) | K1: ROA (%) | L1: ROE (%)
A2: FY2024 | B2: 153670 | D2: 26248 | E2: =D2/B2 -> 0.17080757 | F2: 137814 | G2: 88461 | H2: 89432 | I2: 38794 | J2: =H2/I2 -> 2.3053049 | K2: =D2/F2 -> 0.1904596 | L2: =D2/G2 -> 0.29671833
A3: FY2025 | B3: 162990 | C3: =(B3-B2)/B2 -> 0.060649444 | D3: 26750 | E3: =D3/B3 -> 0.1641205 | F3: 148903 | G3: 96203 | H3: 97099 | I3: 42850 | J3: =H3/I3 -> 2.266021 | K3: =D3/F3 -> 0.17964715 | L3: =D3/G3 -> 0.27805786
A4: FY2026 | B4: 178650 | C4: =(B4-B3)/B3 -> 0.096079514 | D4: 29474 | E4: =D4/B4 -> 0.16498181 | F4: 155967 | G4: 93297 | H4: 103489 | I4: 52322 | J4: =H4/I4 -> 1.9779252 | K4: =D4/F4 -> 0.18897587 | L4: =D4/G4 -> 0.31591584

Sheet Analysis
A1: Financial Year | B1: Revenue (₹ Cr) | C1: Revenue Growth (%) | D1: Net Profit (₹ Cr) | E1: Net Profit Margin (%) | F1: Current Ratio (x) | G1: ROA (%) | H1: ROE (%)
A2: FY2024 | B2: ='Raw Data'!B2 -> 153670 | D2: ='Raw Data'!D2 -> 26248 | E2: ='Raw Data'!E2 -> 0.17080757 | F2: ='Raw Data'!J2 -> 2.3053049 | G2: ='Raw Data'!K2 -> 0.1904596 | H2: ='Raw Data'!L2 -> 0.29671833
A3: FY2025 | B3: ='Raw Data'!B3 -> 162990 | C3: ='Raw Data'!C3 -> 0.060649444 | D3: ='Raw Data'!D3 -> 26750 | E3: ='Raw Data'!E3 -> 0.1641205 | F3: ='Raw Data'!J3 -> 2.266021 | G3: ='Raw Data'!K3 -> 0.17964715 | H3: ='Raw Data'!L3 -> 0.27805786
A4: FY2026 | B4: ='Raw Data'!B4 -> 178650 | C4: ='Raw Data'!C4 -> 0.096079514 | D4: ='Raw Data'!D4 -> 29474 | E4: ='Raw Data'!E4 -> 0.16498181 | F4: ='Raw Data'!J4 -> 1.9779252 | G4: ='Raw Data'!K4 -> 0.18897587 | H4: ='Raw Data'!L4 -> 0.31591584
A6: Key Financial Findings
A7: Revenue Growth | B7: Revenue growth improved from 6.06% in FY2025 to 9.61% in FY2026.
A8: Profitability | B8: Net profit margin declined from 17.08% in FY2024 to 16.41% in FY2025, before improving slightly to 16.50% in FY2026.
A9: Liquidity | B9: Current ratio declined from 2.31x to 1.98x, indicating a reduction in short-term liquidity.
A10: Return on Assets | B10: ROA declined from 19.05% to 17.97% and then improved to 18.90% in FY2026.
A11: Return on Equity | B11: ROE declined in FY2025 but increased to 31.59% in FY2026, indicating improved returns to shareholders.

Sheet Forecast
A1: Financial Year | B1: Revenue (₹ Cr) | C1: Growth Rate (%) | D1: Forecast Revenue (₹ Cr) | E1: Net Profit Margin (%) | F1: Forecast Net Profit (₹ Cr)
A2: FY2024 | B2: ='Raw Data'!B2 -> 153670
A3: FY2025 | B3: ='Raw Data'!B3 -> 162990 | C3: ='Raw Data'!C3 -> 0.060649444
A4: FY2026 | B4: ='Raw Data'!B4 -> 178650 | C4: ='Raw Data'!C4 -> 0.096079514
A5: FY2027E | C5: =AVERAGE(C3:C4) -> 0.078364479 | D5: =B4*(1+C5) -> 192649.81 | E5: =AVERAGE('Raw Data'!E2:E4) -> 0.16663663 | F5: =D5*E5 -> 32102.515
A6: FY2028E | C6: =C5 -> 0.078364479 | D6: =D5*(1+C6) -> 207746.72 | E6: =E5 -> 0.16663663 | F6: =D6*E6 -> 34618.212

Sheet Dashboard
A1: Infosys Financial Analysis Dashboard
A3: Key Financial Metrics
A4: Revenue FY2026 | B4: ='Raw Data'!B4 -> 178650
A5: Net Profit FY2026 | B5: ='Raw Data'!D4 -> 29474
A6: Revenue Growth FY2026 | B6: ='Raw Data'!C4 -> 0.096079514
A7: Net Profit Margin FY2026 | B7: ='Raw Data'!E4 -> 0.16498181
A8: Current Ratio FY2026 | B8: ='Raw Data'!J4 -> 1.9779252
A9: ROA FY2026 | B9: ='Raw Data'!K4 -> 0.18897587
A10: ROE FY2026 | B10: ='Raw Data'!L4 -> 0.31591584
A12: Revenue & Profitability Trend
A13: Financial Year | B13: Revenue (₹ Cr) | C13: Net Profit (₹ Cr)
A14: FY2024 | B14: ='Raw Data'!B2 -> 153670 | C14: ='Raw Data'!D2 -> 26248
A15: FY2025 | B15: ='Raw Data'!B3 -> 162990 | C15: ='Raw Data'!D3 -> 26750
A16: FY2026 | B16: ='Raw Data'!B4 -> 178650 | C16: ='Raw Data'!D4 -> 29474
A18: Revenue Forecast
A19: Financial Year | B19: Forecast Revenue (₹ Cr) | C19: Forecast Net Profit (₹ Cr)
A20: FY2027E | B20: =Forecast!D5 -> 192649.81 | C20: =Forecast!F5 -> 32102.515
A21: FY2028E | B21: =Forecast!D6 -> 207746.72 | C21: =Forecast!F6 -> 34618.212
A33: Key Takeaways
A34: Revenue increased from ₹1,53,670 Cr in FY2024 to ₹1,78,650 Cr in FY2026.
A35: Revenue growth improved to 9.61% in FY2026.
A36: Net profit increased to ₹29,474 Cr in FY2026.
A37: ROE improved to 31.59% in FY2026.
A38: Forecast revenue is ₹1,92,650 Cr for FY2027E and ₹2,07,747 Cr for FY2028E.

Sheet Sources
A1: Sources & Methodology
A3: Company | B3: Infosys Limited
A4: Financial Basis | B4: Consolidated IFRS, INR (₹ crore)
A5: Historical Period | B5: FY2024–FY2026
A7: Official Financial Data | B7: Infosys 3-Year Overview / Financial Data
A8: Annual Report | B8: Infosys Annual Report 2025-26
A10: Forecast Method | B10: Average of FY2025 and FY2026 revenue growth
A11: Forecast Profit Method | B11: Average net profit margin of FY2024–FY2026
